[{
        "id": 0,
        "titre": "Riding cities",
        "description":"html/css",
        "image": "ridingcities.png"
      },
      {
        "id": 1,
        "titre": "Booki",
        "description":"Html/css",
        "image": "booki.png"
      },
      {
        "id": 2,
        "titre": "OhmyFood",
        "description":"Html/css + animation",
        "image": "ohmyfood.png"
      },
      
    {
        "id": 3,
        "titre": "Print it js",
        "description":"Animation",
        "image": "printit.png"
      },
      {
        "id": 4,
        "titre": "Sophie Buel - Architecte d'intérieur",
        "description": "javascript gestion operation CRUD",
        "image":"sbuel.png"
      },
      {
        "id": 5,
        "titre": "MenuMaker",
        "description":"initiation a la gestion de projet",
        "image": "projet.jpg"
      },
      {
        "id": 6,
        "titre": "Kasa",
        "description": "SPA React",
        "image": "kasa.png"
      }, 
      {
        "id": 7,
        "titre": "Nina Carducci",
        "description":"Optimisation SEO",
        "image": "seo.png"
      },
      {
        "id": 8,
        "titre": "77events",
        "description":"Debugging",
        "image": "77event.png"
      },
      {
        "id": 9,
        "titre": "Argentbank",
        "description": "SPA React avec gestion de state global via redux",
        "image": "argbank.png"
      }
      
      
      
     
]